cronos_ai_agent_dev/__init__.py
cronos_ai_agent_dev/assistant.py
cronos_ai_agent_dev/config.py
cronos_ai_agent_dev/error_handler.py
cronos_ai_agent_dev/handlers.py
cronos_ai_agent_dev/logger.py
cronos_ai_agent_dev/memory.py
cronos_ai_agent_dev/tools.py
cronos_ai_agent_dev/bots/__init__.py
cronos_ai_agent_dev/bots/discord/__init__.py
cronos_ai_agent_dev/bots/slack/__init__.py
cronos_ai_agent_dev/bots/telegram/__init__.py
cronos_ai_agent_dev/bots/telegram/handlers.py
cronos_ai_agent_dev/bots/telegram/telegram_bot.py
cronos_ai_agent_dev/bots/wechat/__init__.py
cronos_ai_agent_dev/functions/__init__.py
cronos_ai_agent_dev/functions/base_function.py
cronos_ai_agent_dev/functions/bonding_transaction_function.py
cronos_ai_agent_dev/functions/cdc_agent_sdk_function.py
cronos_ai_agent_dev/functions/coingecko_price_function.py
cronos_ai_agent_dev/functions/cronos_zkevm_knowledge_function.py
cronos_ai_agent_dev/functions/crypto_ids_function.py
cronos_ai_agent_dev/functions/erc20_balance_function.py
cronos_ai_agent_dev/functions/h2_token_price_function.py
cronos_ai_agent_dev/functions/h2_whitelist_function.py
cronos_ai_agent_dev/functions/native_balance_function.py
cronos_ai_agent_dev/functions/sentio_price_function.py
cronos_ai_agent_dev/functions/transaction_parser_function.py
cronos_ai_agent_dev/functions/vvs_recent_swaps_function.py
cronos_ai_agent_dev/functions/subgraph/__init__.py
cronos_ai_agent_dev/functions/subgraph/vvs_swaps_query.py
cronos_ai_agent_dev/local/__init__.py
cronos_ai_agent_dev/local/base_assistant.py
cronos_ai_agent_dev/local/base_tools.py
cronos_ai_agent_dev/local/custom_assistant.py
cronos_ai_agent_dev/local/custom_tools.py
cronos_ai_agent_dev/prompts/__init__.py
cronos_ai_agent_dev/prompts/common_prompt.py
cronos_ai_agent_dev/prompts/core_prompt.py
cronos_ai_agent_dev/prompts/price_query_prompt.py
cronos_ai_agent_dev/prompts/recent_swaps_analysis_prompt.py
cronos_ai_agent_dev/prompts/wallet_query_prompt.py
cronos_ai_agent_dev/remote/__init__.py
cronos_ai_agent_dev-0.1.4.dist-info/LICENSE
cronos_ai_agent_dev-0.1.4.dist-info/METADATA
cronos_ai_agent_dev-0.1.4.dist-info/WHEEL
cronos_ai_agent_dev-0.1.4.dist-info/top_level.txt
cronos_ai_agent_dev-0.1.4.dist-info/RECORD
